{"updated":"2026-07-23T19:44:12Z","source":"nasstatus.faa.gov","counts":{"ground_stops":0,"delay_programs":5},"programs":[{"airport":"AUS","icao":"KAUS","program":"ground_delay","reason":"runway construction","bounds":{"avg":31,"max":92},"end_time":"","since":1784825351},{"airport":"BOS","icao":"KBOS","program":"ground_delay","reason":"wind","bounds":{"avg":40,"max":103},"end_time":"","since":1784828347},{"airport":"SAN","icao":"KSAN","program":"ground_delay","reason":"VOLUME","bounds":{"avg":28,"max":70},"end_time":"","since":1784810646},{"airport":"SFO","icao":"KSFO","program":"ground_delay","reason":"other","bounds":{"avg":55,"max":120},"end_time":"","since":1784809758},{"airport":"TEB","icao":"KTEB","program":"arr_dep","reason":"TM Initiatives:SWAP:WX","bounds":{"min":16,"max":30},"end_time":"","since":1784834651}]}